{"is_source_file": true, "format": "JavaScript (React)", "description": "This file defines a React functional component named 'App' that implements a simple counter UI with increment, decrement, and reset functionalities. It includes state management using useState, memoized formatting with useMemo, and renders a styled counter interface with accessibility features.", "external_files": ["./App.css"], "external_methods": ["React.useState", "React.useMemo"], "published": ["App"], "classes": [], "methods": [{"name": "App()", "description": "Main functional component that renders the counter UI with internal state and control methods.", "scope": "", "scopeKind": ""}, {"name": "increment", "description": "Increases the counter value by one."}, {"name": "decrement", "description": "Decreases the counter value by one."}, {"name": "reset", "description": "Resets the counter value to zero."}], "calls": ["setCount", "useMemo", "useState"], "search-terms": ["React", "counter", "useState", "useMemo", "increment", "decrement", "reset", "App component"], "state": 2, "file_id": 4, "knowledge_revision": 26, "git_revision": "44ca7186a73281e79d643d6428e0d9cac42dae43", "revision_history": [{"23": "44ca7186a73281e79d643d6428e0d9cac42dae43"}, {"26": "44ca7186a73281e79d643d6428e0d9cac42dae43"}], "ctags": [{"_type": "tag", "name": "App", "path": "/home/kavia/workspace/code-generation/simple-counter-app-339133-339156/counter_frontend/src/App.js", "pattern": "/^function App() {$/", "language": "JavaScript", "kind": "function", "signature": "()"}], "hash": "5b2ee6c7335d6d1d5300b91f987fd476", "format-version": 4, "code-base-name": "counter_frontend", "filename": "counter_frontend/src/App.js"}